README.md
setup.py
imm_utils.egg-info/PKG-INFO
imm_utils.egg-info/SOURCES.txt
imm_utils.egg-info/dependency_links.txt
imm_utils.egg-info/entry_points.txt
imm_utils.egg-info/top_level.txt
utils/__init__.py
utils/areas.py
utils/canada.py
utils/files.py
utils/language.py
utils/pdf.py
utils/setbase.py
utils/utils.py
utils/word.py
utils/wordtpl.py